lcpy/__init__.py
lc_py-2.0.1.dist-info/LICENSE
lc_py-2.0.1.dist-info/METADATA
lc_py-2.0.1.dist-info/WHEEL
lc_py-2.0.1.dist-info/top_level.txt
lc_py-2.0.1.dist-info/RECORD
